[{"ad": "Aysel H\u0259s\u0259nova", "pese": "Qrafik dizayner", "maas": 1200}, {"ad": "Murad M\u0259mm\u0259dov", "pese": "Frontend proqram\u00e7\u0131", "maas": 1800}, {"ad": "N\u0259rmin \u018fliyeva", "pese": "M\u00fchasib", "maas": 1400}, {"ad": "Rauf Quliyev", "pese": "Backend m\u00fch\u0259ndis", "maas": 2200}, {"ad": "G\u00fcnel Rzayeva", "pese": "M\u0259kt\u0259b m\u00fc\u0259llimi", "maas": 800}, {"ad": "Orxan Hac\u0131yev", "pese": "Sistem administratoru", "maas": 1600}, {"ad": "Sevinc C\u0259f\u0259rova", "pese": "HR m\u00fct\u0259x\u0259ssis", "maas": 1300}, {"ad": "Elvin \u0130smay\u0131lov", "pese": "Mobil developer", "maas": 2100}, {"ad": "L\u0259man Qas\u0131mova", "pese": "Kontent menecer", "maas": 1000}, {"ad": "Kamran V\u0259liyev", "pese": "Data analitik", "maas": 2300}, {"ad": "\u015e\u0259bn\u0259m \u018fl\u0259kb\u0259rova", "pese": "Marketinq m\u00fct\u0259x\u0259ssisi", "maas": 1500}, {"ad": "Emin S\u0259f\u0259rov", "pese": "DevOps m\u00fch\u0259ndis", "maas": 2400}, {"ad": "Ayg\u00fcn H\u00fcseynova", "pese": "UX/UI dizayner", "maas": 1700}, {"ad": "Samir S\u0259m\u0259dov", "pese": "Sat\u0131\u015f meneceri", "maas": 1100}, {"ad": "Nigar M\u0259mm\u0259dli", "pese": "SMM m\u00fct\u0259x\u0259ssisi", "maas": 1200}, {"ad": "Tural Qarayev", "pese": "Fullstack developer", "maas": 2500}, {"ad": "Z\u0259hra Abdullayeva", "pese": "Projekt menecer", "maas": 2000}, {"ad": "El\u00e7in Muradov", "pese": "Mexanik m\u00fch\u0259ndis", "maas": 1600}, {"ad": "Leyla R\u00fcst\u0259mova", "pese": "T\u0259rc\u00fcm\u0259\u00e7i", "maas": 900}, {"ad": "F\u0259rid \u015eirinov", "pese": "Kibert\u0259hl\u00fck\u0259sizlik \u00fczr\u0259 m\u00fct\u0259x\u0259ssis", "maas": 2600}]